Metadata-Version: 2.4
Name: gearpy
Version: 1.2.0
Summary: Python library for mechanical transmission analysis
Author-email: Andrea Blengino <ing.andrea.blengino@protonmail.com>
Maintainer-email: Andrea Blengino <ing.andrea.blengino@protonmail.com>
License:                     GNU GENERAL PUBLIC LICENSE
Project-URL: Homepage, https://github.com/AndreaBlengino/gearpy
Project-URL: Documentation, https://gearpy.readthedocs.io/en/latest/index.html
Project-URL: Issues, https://github.com/AndreaBlengino/gearpy/issues
Project-URL: Repository, https://github.com/AndreaBlengino/gearpy
Classifier: Development Status :: 5 - Production/Stable
Classifier: Intended Audience :: Education
Classifier: Intended Audience :: Manufacturing
Classifier: License :: OSI Approved :: GNU General Public License v3 (GPLv3)
Classifier: Operating System :: OS Independent
Classifier: Programming Language :: Python
Classifier: Programming Language :: Python :: 3.10
Classifier: Programming Language :: Python :: 3.11
Classifier: Programming Language :: Python :: 3.12
Classifier: Programming Language :: Python :: 3.13
Classifier: Programming Language :: Python :: 3.14
Classifier: Topic :: Scientific/Engineering
Requires-Python: >=3.10
License-File: LICENSE
Requires-Dist: matplotlib!=3.9.1,>=3.5
Requires-Dist: numpy>=1.20
Requires-Dist: pandas>=1.2
Requires-Dist: scipy!=1.11.0,!=1.14.0rc1,>=1.6
Provides-Extra: doc
Requires-Dist: furo==2024.8.6; extra == "doc"
Requires-Dist: m2r2==0.3.3.post2; extra == "doc"
Requires-Dist: sphinx==8.1.3; extra == "doc"
Requires-Dist: sphinx-copybutton==0.5.2; extra == "doc"
Requires-Dist: docutils==0.20.1; extra == "doc"
Provides-Extra: test
Requires-Dist: coverage==7.6.3; extra == "test"
Requires-Dist: hypothesis==6.112.1; extra == "test"
Requires-Dist: pytest==8.3.3; extra == "test"
Requires-Dist: pytest-cov==5.0.0; extra == "test"
Requires-Dist: pytest-xdist==3.6.1; extra == "test"
Dynamic: license-file
